Combinational Circuits/multiplexers/2to1mux/program.v
module mux2to1 (
    input [1:0]in,
    input sel,
    output out
);
    assign out = in[sel];
endmodule

Combinational Circuits/multiplexers/2to1mux/testProgram.v
module testMux4to1;
    reg [1:0] in;
    reg sel;
    wire out;

    mux2to1 dut(.in(in),.sel(sel),.out(out));

    reg clk;
    reg rst;

    initial begin
        clk = 0;
        rst = 1;
        #20 rst = 0;
    end
    always begin
        #10 clk = ~clk;
    end
    reg [2:0] i;
    always @(posedge clk , posedge rst) begin
        if(rst)begin
            i <= 0;
        end
        else begin
            in <= $random%4;
            sel <=$random%2;
            i = i+1;
            if(i == 5)begin
                #10 $finish;
            end
        end
    end
    initial begin
        $monitor("%d: in=%b,sel=%b,out=%b",$time,in,sel,out);
        $dumpfile("waveform.vcd");
        $dumpvars();
    end
endmodule

Combinational Circuits/multiplexers/2to1mux/waveform.vcd
$date
	Wed Feb 26 23:05:40 2025
$end
$version
	Icarus Verilog
$end
$timescale
	1s
$end
$scope module testMux4to1 $end
$var wire 1 ! out $end
$var reg 1 " clk $end
$var reg 3 # i [2:0] $end
$var reg 2 $ in [1:0] $end
$var reg 1 % rst $end
$var reg 1 & sel $end
$scope module dut $end
$var wire 2 ' in [1:0] $end
$var wire 1 & sel $end
$var wire 1 ! out $end
$upscope $end
$upscope $end
$enddefinitions $end
$comment Show the parameter values. $end
$dumpall
$end
#0
$dumpvars
bx '
x&
1%
bx $
bx #
0"
x!
$end
#10
b0 #
1"
#20
0"
0%
#30
0!
1&
b0 $
b0 '
b1 #
1"
#40
0"
#50
b1 $
b1 '
b10 #
1"
#60
0"
#70
b11 #
1"
#80
0"
#90
1!
0&
b100 #
1"
#100
0"
#110
0!
1&
b101 #
1"
