Combinational Circuits/adders/bcdAdder/program.v
module carryGeneration (
    input cin,p0,p1,p2,p3,g0,g1,g2,g3,
    output c1,c2,c3,c4
);  
    wire c0;
    assign c0 = cin;
    assign c1 = g0 | (p0 & c0);
    assign c2 = g1 | (p1 & g0) | (p0 & p1 & c0);
    assign c3 = g2 | (p2 & g1) | (p1 & p2 & g0) | (p0 & p1 & p2 & c0);
    assign c4 = g3 | (p3 & g2) | (p2 & p3 & g1) | (p1 & p2 & p3 & g0) | (p0 & p1 & p2 & p3 & c0);

endmodule

module cla (
    input [3:0]a,b,
    input cin,
    output [3:0] sum,
    output cout
);
    wire g0,g1,g2,g3,p0,p1,p2,p3;
    wire c1,c2,c3,c4;

    assign g0 = a[0]&b[0];
    assign g1 = a[1]&b[1];
    assign g2 = a[2]&b[2];
    assign g3 = a[3]&b[3];

    assign p0 = a[0]^b[0];
    assign p1 = a[1]^b[1];
    assign p2 = a[2]^b[2];
    assign p3 = a[3]^b[3];

    carryGeneration cg(cin,p0,p1,p2,p3,g0,g1,g2,g3,c1,c2,c3,c4);

    assign sum[0] = p0 ^ cin;
    assign sum[1] = p1 ^ c1;
    assign sum[2] = p2 ^ c2;
    assign sum[3] = p3 ^ c3;
    assign cout = c4;
endmodule

module bcdAdder (
    input [3:0]a,b,
    input cin,
    output [3:0]sum,
    output cout
);
    wire [3:0]z,x;
    wire k,c1,c2;
    cla cla1(a,b,cin,z,k);
    assign c1 = (z[3]&z[1]) | (z[3]&z[2]) | k  ;
    assign x = {1'b0,c1,c1,1'b0};
    cla cla2(x,z,1'b0,sum,c2);
    assign cout = c1;
endmodule

Combinational Circuits/adders/bcdAdder/testProgram.v
module testBench;
    reg [3:0]a,b;
    reg cin;
    wire cout;
    wire [3:0]sum;
    bcdAdder dut(a,b,cin,sum,cout);
    reg clk;
    reg rst;

    initial begin
        clk = 0;
        rst = 1;
        #20 rst =0;
    end
    always begin
        #10 clk = ~clk;
    end
    reg [7:0]o ;
    always @(posedge clk ,posedge rst) begin
        if(rst)begin
            o <=0;
        end
        else
        begin
            a=$random%16;
            b=$random%16;
            cin=$random%2;
            o <= o+1;

            if(o == 20)begin
                #10 $finish;
            end

        end
    end
        initial begin
            $monitor("%d: a=%b,b=%b,cin=%b,sum=%b,cout=%b",$time,a,b,cin,sum,cout);
            $dumpfile("waveform.vcd");
            $dumpvars();
        end
endmodule

Combinational Circuits/adders/bcdAdder/waveform.vcd
$date
	Thu Feb 27 15:26:33 2025
$end
$version
	Icarus Verilog
$end
$timescale
	1s
$end
$scope module testBench $end
$var wire 4 ! sum [3:0] $end
$var wire 1 " cout $end
$var reg 4 # a [3:0] $end
$var reg 4 $ b [3:0] $end
$var reg 1 % cin $end
$var reg 1 & clk $end
$var reg 8 ' o [7:0] $end
$var reg 1 ( rst $end
$scope module dut $end
$var wire 4 ) a [3:0] $end
$var wire 4 * b [3:0] $end
$var wire 1 + c1 $end
$var wire 1 % cin $end
$var wire 1 " cout $end
$var wire 4 , z [3:0] $end
$var wire 4 - x [3:0] $end
$var wire 4 . sum [3:0] $end
$var wire 1 / k $end
$var wire 1 0 c2 $end
$scope module cla1 $end
$var wire 4 1 a [3:0] $end
$var wire 4 2 b [3:0] $end
$var wire 1 % cin $end
$var wire 1 / cout $end
$var wire 1 3 g0 $end
$var wire 1 4 g1 $end
$var wire 1 5 g2 $end
$var wire 1 6 g3 $end
$var wire 1 7 p0 $end
$var wire 1 8 p1 $end
$var wire 1 9 p2 $end
$var wire 1 : p3 $end
$var wire 4 ; sum [3:0] $end
$var wire 1 < c4 $end
$var wire 1 = c3 $end
$var wire 1 > c2 $end
$var wire 1 ? c1 $end
$scope module cg $end
$var wire 1 @ c0 $end
$var wire 1 ? c1 $end
$var wire 1 > c2 $end
$var wire 1 = c3 $end
$var wire 1 < c4 $end
$var wire 1 % cin $end
$var wire 1 3 g0 $end
$var wire 1 4 g1 $end
$var wire 1 5 g2 $end
$var wire 1 6 g3 $end
$var wire 1 7 p0 $end
$var wire 1 8 p1 $end
$var wire 1 9 p2 $end
$var wire 1 : p3 $end
$upscope $end
$upscope $end
$scope module cla2 $end
$var wire 4 A a [3:0] $end
$var wire 4 B b [3:0] $end
$var wire 1 C cin $end
$var wire 1 0 cout $end
$var wire 1 D g0 $end
$var wire 1 E g1 $end
$var wire 1 F g2 $end
$var wire 1 G g3 $end
$var wire 1 H p0 $end
$var wire 1 I p1 $end
$var wire 1 J p2 $end
$var wire 1 K p3 $end
$var wire 4 L sum [3:0] $end
$var wire 1 M c4 $end
$var wire 1 N c3 $end
$var wire 1 O c2 $end
$var wire 1 P c1 $end
$scope module cg $end
$var wire 1 Q c0 $end
$var wire 1 P c1 $end
$var wire 1 O c2 $end
$var wire 1 N c3 $end
$var wire 1 M c4 $end
$var wire 1 C cin $end
$var wire 1 D g0 $end
$var wire 1 E g1 $end
$var wire 1 F g2 $end
$var wire 1 G g3 $end
$var wire 1 H p0 $end
$var wire 1 I p1 $end
$var wire 1 J p2 $end
$var wire 1 K p3 $end
$upscope $end
$upscope $end
$upscope $end
$upscope $end
$enddefinitions $end
$comment Show the parameter values. $end
$dumpall
$end
#0
$dumpvars
0Q
0P
xO
xN
xM
bx L
xK
xJ
xI
xH
0G
xF
xE
0D
0C
bx B
b0xx0 A
x@
x?
x>
x=
x<
bx ;
x:
x9
x8
x7
x6
x5
x4
x3
bx 2
bx 1
x0
x/
bx .
b0xx0 -
bx ,
x+
bx *
bx )
1(
bx '
0&
x%
bx $
bx #
x"
bx !
$end
#10
b0 '
1&
#20
0&
0(
#30
b1 '
0N
0O
00
0M
0E
1I
0F
1J
0"
b0 -
b0 A
0+
0K
b110 !
b110 .
b110 L
0=
0H
0/
0<
0>
1?
b110 ,
b110 ;
b110 B
03
04
05
06
17
08
19
0:
1@
1%
b1 $
b1 *
b1 2
b100 #
b100 )
b100 1
1&
#40
0&
#50
b10 '
1J
1"
b110 -
b110 A
1+
1/
1<
b111 !
b111 .
b111 L
0K
1=
1H
1I
1>
b1 ,
b1 ;
b1 B
1:
13
07
18
b1101 $
b1101 *
b1101 2
b11 #
b11 )
b11 1
1&
#60
0&
#70
b11 '
0I
0J
0"
b0 -
b0 A
0+
b1000 !
b1000 .
b1000 L
0/
0<
0H
1K
b1000 ,
b1000 ;
b1000 B
03
17
0:
b10 $
b10 *
b10 2
b101 #
b101 )
b101 1
1&
#80
0&
#90
b100 '
1N
1I
1F
b1010 !
b1010 .
b1010 L
1"
b110 -
b110 A
1+
0J
0K
1/
1<
b100 ,
b100 ;
b100 B
15
09
1:
b110 $
b110 *
b110 2
b1101 #
b1101 )
b1101 1
1&
#100
0&
#110
b101 '
10
1M
0F
1J
1O
b0 !
b0 .
b0 L
1E
0I
0>
1K
b1010 ,
b1010 ;
b1010 B
16
08
0:
b1100 $
b1100 *
b1100 2
1&
#120
0&
#130
b110 '
0/
0<
b1 !
b1 .
b1 L
1H
0?
06
18
b1011 ,
b1011 ;
b1011 B
0@
0%
b101 $
b101 *
b101 2
b110 #
b110 )
b110 1
1&
#140
0&
#150
b111 '
1N
10
1M
0O
1"
b110 -
b110 A
1+
1F
0J
0E
1I
b10 !
b10 .
b10 L
1>
0H
1?
b1100 ,
b1100 ;
b1100 B
13
07
b111 $
b111 *
b111 2
b101 #
b101 )
b101 1
1&
#160
0&
#170
b1000 '
0N
00
0M
0O
1/
1<
b111 !
b111 .
b111 L
1H
0F
1J
0E
1I
0K
0?
b1 ,
b1 ;
b1 B
03
05
17
19
14
08
1:
b10 $
b10 *
b10 2
b1111 #
b1111 )
b1111 1
1&
#180
0&
#190
b1001 '
10
1M
1N
1K
1I
b11 !
b11 .
b11 L
1F
0J
1"
b110 -
b110 A
1+
0=
0/
0<
b1101 ,
b1101 ;
b1101 B
0>
04
b101 $
b101 *
b101 2
b1000 #
b1000 )
b1000 1
1&
#200
0&
#210
b1010 '
10
1M
1O
1/
1<
1E
0I
1K
1=
0F
1J
b1 !
b1 .
b1 L
1H
1?
16
0:
13
15
07
09
b1011 ,
b1011 ;
b1011 B
1@
1%
b1101 $
b1101 *
b1101 2
b1101 #
b1101 )
b1101 1
1&
#220
0&
#230
b1011 '
1N
10
1M
0O
1F
0J
1"
b110 -
b110 A
1+
0E
1I
0/
0<
0=
1K
b11 !
b11 .
b11 L
1>
1H
0?
03
17
14
05
06
1:
b1101 ,
b1101 ;
b1101 B
0@
0%
b1010 $
b1010 *
b1010 2
b11 #
b11 )
b11 1
1&
#240
0&
#250
b1100 '
1O
0F
1J
1E
0I
b1 !
b1 .
b1 L
0>
1H
0?
04
07
18
b1011 ,
b1011 ;
b1011 B
1@
1%
b0 #
b0 )
b0 1
1&
#260
0&
#270
b1101 '
1N
10
1M
1O
1"
b110 -
b110 A
1+
b0 !
b0 .
b0 L
1=
0H
1K
1E
0I
0F
1J
1?
1>
b1010 ,
b1010 ;
b1010 B
17
0:
14
08
19
b11 $
b11 *
b11 2
b110 #
b110 )
b110 1
1&
#280
0&
#290
b1110 '
1N
1O
10
1M
1E
0I
1"
b110 -
b110 A
1+
b101 !
b101 .
b101 L
0=
1K
1H
1F
0J
b1111 ,
b1111 ;
b1111 B
1:
13
07
09
b1011 $
b1011 *
b1011 2
b11 #
b11 )
b11 1
1&
#300
0&
#310
b1111 '
00
0M
0K
0N
0O
1/
1<
b111 !
b111 .
b111 L
1=
0E
1I
0F
1J
b1 ,
b1 ;
b1 B
0?
19
03
b1110 $
b1110 *
b1110 2
b10 #
b10 )
b10 1
1&
#320
0&
#330
b10000 '
1N
1O
1E
0I
b1000 !
b1000 .
b1000 L
0H
1?
13
b10 ,
b10 ;
b10 B
0@
0%
b11 $
b11 *
b11 2
b1111 #
b1111 )
b1111 1
1&
#340
0&
#350
b10001 '
00
0M
1F
0J
0=
b1100 !
b1100 .
b1100 L
0K
0>
b110 ,
b110 ;
b110 B
0?
04
16
18
0:
03
b1100 $
b1100 *
b1100 2
b1010 #
b1010 )
b1010 1
1&
#360
0&
#370
b10010 '
10
1M
0/
0<
b1 !
b1 .
b1 L
1H
0F
1J
1K
b1011 ,
b1011 ;
b1011 B
06
17
09
1:
b1 $
b1 *
b1 2
1&
#380
0&
#390
b10011 '
00
0M
1/
1<
0F
1J
0K
b1000 !
b1000 .
b1000 L
0H
1?
0>
16
0:
08
b10 ,
b10 ;
b10 B
1@
1%
b1001 $
b1001 *
b1001 2
b1000 #
b1000 )
b1000 1
1&
#400
0&
#410
b10100 '
10
1M
1N
1K
0O
1F
0J
1"
b110 -
b110 A
1+
0/
0<
0E
1I
1=
b10 !
b10 .
b10 L
1>
0H
0?
07
14
15
06
b1100 ,
b1100 ;
b1100 B
0@
0%
b110 $
b110 *
b110 2
b110 #
b110 )
b110 1
1&
#420
0&
#430
b10101 '
00
0M
0K
1O
1/
1<
0=
1F
0J
1E
0I
b1101 !
b1101 .
b1101 L
0>
1H
05
19
04
16
18
b111 ,
b111 ;
b111 B
1@
1%
b1010 $
b1010 *
b1010 2
b1100 #
b1100 )
b1100 1
1&
